objtoolbox/__init__.py
objtoolbox/merge.py
objtoolbox/storage.py
objtoolbox/utils.py
objtoolbox-0.0.11.dist-info/LICENSE
objtoolbox-0.0.11.dist-info/METADATA
objtoolbox-0.0.11.dist-info/WHEEL
objtoolbox-0.0.11.dist-info/top_level.txt
objtoolbox-0.0.11.dist-info/RECORD
