Metadata-Version: 2.1
Name: objtoolbox
Version: 0.0.11
Summary: Advanced utility functions for python objects
Author-email: Jona Ruof <jona.ruof@uni-ulm.de>
Project-URL: Homepage, https://github.com/joruof/objtoolbox
Project-URL: Bug Tracker, https://github.com/joruof/objtoolbox/issues
Classifier: Programming Language :: Python :: 3
Requires-Python: >=3.6
License-File: LICENSE
Requires-Dist: numpy >=1.20
Requires-Dist: zarr >=2.14.2
